[{"providerCode": "MUFG", "date": {"year": 2022, "month": 3, "day": 1}, "baseCurrencyCode": "CNY", "quoteCurrencyCode": "JPY", "ask": {"currencyCode": "JPY", "units": "18", "nanos": 570000000}, "bid": {"currencyCode": "JPY", "units": "17", "nanos": 970000000}, "mid": {"currencyCode": "JPY", "units": "18", "nanos": 270000000}}, {"providerCode": "MUFG", "date": {"year": 2022, "month": 3, "day": 2}, "baseCurrencyCode": "CNY", "quoteCurrencyCode": "JPY", "ask": {"currencyCode": "JPY", "units": "18", "nanos": 500000000}, "bid": {"currencyCode": "JPY", "units": "17", "nanos": 900000000}, "mid": {"currencyCode": "JPY", "units": "18", "nanos": 200000000}}, {"providerCode": "MUFG", "date": {"year": 2022, "month": 3, "day": 3}, "baseCurrencyCode": "CNY", "quoteCurrencyCode": "JPY", "ask": {"currencyCode": "JPY", "units": "18", "nanos": 590000000}, "bid": {"currencyCode": "JPY", "units": "17", "nanos": 990000000}, "mid": {"currencyCode": "JPY", "units": "18", "nanos": 290000000}}, {"providerCode": "MUFG", "date": {"year": 2022, "month": 3, "day": 4}, "baseCurrencyCode": "CNY", "quoteCurrencyCode": "JPY", "ask": {"currencyCode": "JPY", "units": "18", "nanos": 550000000}, "bid": {"currencyCode": "JPY", "units": "17", "nanos": 950000000}, "mid": {"currencyCode": "JPY", "units": "18", "nanos": 250000000}}, {"providerCode": "MUFG", "date": {"year": 2022, "month": 3, "day": 7}, "baseCurrencyCode": "CNY", "quoteCurrencyCode": "JPY", "ask": {"currencyCode": "JPY", "units": "18", "nanos": 470000000}, "bid": {"currencyCode": "JPY", "units": "17", "nanos": 870000000}, "mid": {"currencyCode": "JPY", "units": "18", "nanos": 170000000}}, {"providerCode": "MUFG", "date": {"year": 2022, "month": 3, "day": 8}, "baseCurrencyCode": "CNY", "quoteCurrencyCode": "JPY", "ask": {"currencyCode": "JPY", "units": "18", "nanos": 570000000}, "bid": {"currencyCode": "JPY", "units": "17", "nanos": 970000000}, "mid": {"currencyCode": "JPY", "units": "18", "nanos": 270000000}}, {"providerCode": "MUFG", "date": {"year": 2022, "month": 3, "day": 9}, "baseCurrencyCode": "CNY", "quoteCurrencyCode": "JPY", "ask": {"currencyCode": "JPY", "units": "18", "nanos": 630000000}, "bid": {"currencyCode": "JPY", "units": "18", "nanos": 30000000}, "mid": {"currencyCode": "JPY", "units": "18", "nanos": 330000000}}, {"providerCode": "MUFG", "date": {"year": 2022, "month": 3, "day": 10}, "baseCurrencyCode": "CNY", "quoteCurrencyCode": "JPY", "ask": {"currencyCode": "JPY", "units": "18", "nanos": 660000000}, "bid": {"currencyCode": "JPY", "units": "18", "nanos": 60000000}, "mid": {"currencyCode": "JPY", "units": "18", "nanos": 360000000}}, {"providerCode": "MUFG", "date": {"year": 2022, "month": 3, "day": 11}, "baseCurrencyCode": "CNY", "quoteCurrencyCode": "JPY", "ask": {"currencyCode": "JPY", "units": "18", "nanos": 690000000}, "bid": {"currencyCode": "JPY", "units": "18", "nanos": 90000000}, "mid": {"currencyCode": "JPY", "units": "18", "nanos": 390000000}}, {"providerCode": "MUFG", "date": {"year": 2022, "month": 3, "day": 14}, "baseCurrencyCode": "CNY", "quoteCurrencyCode": "JPY", "ask": {"currencyCode": "JPY", "units": "18", "nanos": 790000000}, "bid": {"currencyCode": "JPY", "units": "18", "nanos": 190000000}, "mid": {"currencyCode": "JPY", "units": "18", "nanos": 490000000}}, {"providerCode": "MUFG", "date": {"year": 2022, "month": 3, "day": 15}, "baseCurrencyCode": "CNY", "quoteCurrencyCode": "JPY", "ask": {"currencyCode": "JPY", "units": "18", "nanos": 810000000}, "bid": {"currencyCode": "JPY", "units": "18", "nanos": 210000000}, "mid": {"currencyCode": "JPY", "units": "18", "nanos": 510000000}}, {"providerCode": "MUFG", "date": {"year": 2022, "month": 3, "day": 16}, "baseCurrencyCode": "CNY", "quoteCurrencyCode": "JPY", "ask": {"currencyCode": "JPY", "units": "18", "nanos": 840000000}, "bid": {"currencyCode": "JPY", "units": "18", "nanos": 240000000}, "mid": {"currencyCode": "JPY", "units": "18", "nanos": 540000000}}, {"providerCode": "MUFG", "date": {"year": 2022, "month": 3, "day": 17}, "baseCurrencyCode": "CNY", "quoteCurrencyCode": "JPY", "ask": {"currencyCode": "JPY", "units": "19", "nanos": 20000000}, "bid": {"currencyCode": "JPY", "units": "18", "nanos": 420000000}, "mid": {"currencyCode": "JPY", "units": "18", "nanos": 720000000}}, {"providerCode": "MUFG", "date": {"year": 2022, "month": 3, "day": 18}, "baseCurrencyCode": "CNY", "quoteCurrencyCode": "JPY", "ask": {"currencyCode": "JPY", "units": "18", "nanos": 970000000}, "bid": {"currencyCode": "JPY", "units": "18", "nanos": 370000000}, "mid": {"currencyCode": "JPY", "units": "18", "nanos": 670000000}}, {"providerCode": "MUFG", "date": {"year": 2022, "month": 3, "day": 22}, "baseCurrencyCode": "CNY", "quoteCurrencyCode": "JPY", "ask": {"currencyCode": "JPY", "units": "19", "nanos": 140000000}, "bid": {"currencyCode": "JPY", "units": "18", "nanos": 540000000}, "mid": {"currencyCode": "JPY", "units": "18", "nanos": 840000000}}, {"providerCode": "MUFG", "date": {"year": 2022, "month": 3, "day": 23}, "baseCurrencyCode": "CNY", "quoteCurrencyCode": "JPY", "ask": {"currencyCode": "JPY", "units": "19", "nanos": 310000000}, "bid": {"currencyCode": "JPY", "units": "18", "nanos": 710000000}, "mid": {"currencyCode": "JPY", "units": "19", "nanos": 10000000}}, {"providerCode": "MUFG", "date": {"year": 2022, "month": 3, "day": 24}, "baseCurrencyCode": "CNY", "quoteCurrencyCode": "JPY", "ask": {"currencyCode": "JPY", "units": "19", "nanos": 250000000}, "bid": {"currencyCode": "JPY", "units": "18", "nanos": 650000000}, "mid": {"currencyCode": "JPY", "units": "18", "nanos": 950000000}}, {"providerCode": "MUFG", "date": {"year": 2022, "month": 3, "day": 25}, "baseCurrencyCode": "CNY", "quoteCurrencyCode": "JPY", "ask": {"currencyCode": "JPY", "units": "19", "nanos": 440000000}, "bid": {"currencyCode": "JPY", "units": "18", "nanos": 840000000}, "mid": {"currencyCode": "JPY", "units": "19", "nanos": 140000000}}, {"providerCode": "MUFG", "date": {"year": 2022, "month": 3, "day": 28}, "baseCurrencyCode": "CNY", "quoteCurrencyCode": "JPY", "ask": {"currencyCode": "JPY", "units": "19", "nanos": 410000000}, "bid": {"currencyCode": "JPY", "units": "18", "nanos": 810000000}, "mid": {"currencyCode": "JPY", "units": "19", "nanos": 110000000}}, {"providerCode": "MUFG", "date": {"year": 2022, "month": 3, "day": 29}, "baseCurrencyCode": "CNY", "quoteCurrencyCode": "JPY", "ask": {"currencyCode": "JPY", "units": "19", "nanos": 750000000}, "bid": {"currencyCode": "JPY", "units": "19", "nanos": 150000000}, "mid": {"currencyCode": "JPY", "units": "19", "nanos": 450000000}}, {"providerCode": "MUFG", "date": {"year": 2022, "month": 3, "day": 30}, "baseCurrencyCode": "CNY", "quoteCurrencyCode": "JPY", "ask": {"currencyCode": "JPY", "units": "19", "nanos": 500000000}, "bid": {"currencyCode": "JPY", "units": "18", "nanos": 900000000}, "mid": {"currencyCode": "JPY", "units": "19", "nanos": 200000000}}, {"providerCode": "MUFG", "date": {"year": 2022, "month": 3, "day": 31}, "baseCurrencyCode": "CNY", "quoteCurrencyCode": "JPY", "ask": {"currencyCode": "JPY", "units": "19", "nanos": 560000000}, "bid": {"currencyCode": "JPY", "units": "18", "nanos": 960000000}, "mid": {"currencyCode": "JPY", "units": "19", "nanos": 260000000}}]