[{"providerCode": "MUFG", "date": {"year": 2018, "month": 7, "day": 2}, "baseCurrencyCode": "AUD", "quoteCurrencyCode": "JPY", "ask": {"currencyCode": "JPY", "units": "83", "nanos": 930000000}, "bid": {"currencyCode": "JPY", "units": "79", "nanos": 930000000}, "mid": {"currencyCode": "JPY", "units": "81", "nanos": 930000000}}, {"providerCode": "MUFG", "date": {"year": 2018, "month": 7, "day": 3}, "baseCurrencyCode": "AUD", "quoteCurrencyCode": "JPY", "ask": {"currencyCode": "JPY", "units": "83", "nanos": 410000000}, "bid": {"currencyCode": "JPY", "units": "79", "nanos": 410000000}, "mid": {"currencyCode": "JPY", "units": "81", "nanos": 410000000}}, {"providerCode": "MUFG", "date": {"year": 2018, "month": 7, "day": 4}, "baseCurrencyCode": "AUD", "quoteCurrencyCode": "JPY", "ask": {"currencyCode": "JPY", "units": "83", "nanos": 600000000}, "bid": {"currencyCode": "JPY", "units": "79", "nanos": 600000000}, "mid": {"currencyCode": "JPY", "units": "81", "nanos": 600000000}}, {"providerCode": "MUFG", "date": {"year": 2018, "month": 7, "day": 5}, "baseCurrencyCode": "AUD", "quoteCurrencyCode": "JPY", "ask": {"currencyCode": "JPY", "units": "83", "nanos": 490000000}, "bid": {"currencyCode": "JPY", "units": "79", "nanos": 490000000}, "mid": {"currencyCode": "JPY", "units": "81", "nanos": 490000000}}, {"providerCode": "MUFG", "date": {"year": 2018, "month": 7, "day": 6}, "baseCurrencyCode": "AUD", "quoteCurrencyCode": "JPY", "ask": {"currencyCode": "JPY", "units": "83", "nanos": 850000000}, "bid": {"currencyCode": "JPY", "units": "79", "nanos": 850000000}, "mid": {"currencyCode": "JPY", "units": "81", "nanos": 850000000}}, {"providerCode": "MUFG", "date": {"year": 2018, "month": 7, "day": 9}, "baseCurrencyCode": "AUD", "quoteCurrencyCode": "JPY", "ask": {"currencyCode": "JPY", "units": "84", "nanos": 270000000}, "bid": {"currencyCode": "JPY", "units": "80", "nanos": 270000000}, "mid": {"currencyCode": "JPY", "units": "82", "nanos": 270000000}}, {"providerCode": "MUFG", "date": {"year": 2018, "month": 7, "day": 10}, "baseCurrencyCode": "AUD", "quoteCurrencyCode": "JPY", "ask": {"currencyCode": "JPY", "units": "85", "nanos": 60000000}, "bid": {"currencyCode": "JPY", "units": "81", "nanos": 60000000}, "mid": {"currencyCode": "JPY", "units": "83", "nanos": 60000000}}, {"providerCode": "MUFG", "date": {"year": 2018, "month": 7, "day": 11}, "baseCurrencyCode": "AUD", "quoteCurrencyCode": "JPY", "ask": {"currencyCode": "JPY", "units": "84", "nanos": 290000000}, "bid": {"currencyCode": "JPY", "units": "80", "nanos": 290000000}, "mid": {"currencyCode": "JPY", "units": "82", "nanos": 290000000}}, {"providerCode": "MUFG", "date": {"year": 2018, "month": 7, "day": 12}, "baseCurrencyCode": "AUD", "quoteCurrencyCode": "JPY", "ask": {"currencyCode": "JPY", "units": "84", "nanos": 610000000}, "bid": {"currencyCode": "JPY", "units": "80", "nanos": 610000000}, "mid": {"currencyCode": "JPY", "units": "82", "nanos": 610000000}}, {"providerCode": "MUFG", "date": {"year": 2018, "month": 7, "day": 13}, "baseCurrencyCode": "AUD", "quoteCurrencyCode": "JPY", "ask": {"currencyCode": "JPY", "units": "85", "nanos": 620000000}, "bid": {"currencyCode": "JPY", "units": "81", "nanos": 620000000}, "mid": {"currencyCode": "JPY", "units": "83", "nanos": 620000000}}, {"providerCode": "MUFG", "date": {"year": 2018, "month": 7, "day": 17}, "baseCurrencyCode": "AUD", "quoteCurrencyCode": "JPY", "ask": {"currencyCode": "JPY", "units": "85", "nanos": 350000000}, "bid": {"currencyCode": "JPY", "units": "81", "nanos": 350000000}, "mid": {"currencyCode": "JPY", "units": "83", "nanos": 350000000}}, {"providerCode": "MUFG", "date": {"year": 2018, "month": 7, "day": 18}, "baseCurrencyCode": "AUD", "quoteCurrencyCode": "JPY", "ask": {"currencyCode": "JPY", "units": "85", "nanos": 440000000}, "bid": {"currencyCode": "JPY", "units": "81", "nanos": 440000000}, "mid": {"currencyCode": "JPY", "units": "83", "nanos": 440000000}}, {"providerCode": "MUFG", "date": {"year": 2018, "month": 7, "day": 19}, "baseCurrencyCode": "AUD", "quoteCurrencyCode": "JPY", "ask": {"currencyCode": "JPY", "units": "85", "nanos": 520000000}, "bid": {"currencyCode": "JPY", "units": "81", "nanos": 520000000}, "mid": {"currencyCode": "JPY", "units": "83", "nanos": 520000000}}, {"providerCode": "MUFG", "date": {"year": 2018, "month": 7, "day": 20}, "baseCurrencyCode": "AUD", "quoteCurrencyCode": "JPY", "ask": {"currencyCode": "JPY", "units": "84", "nanos": 970000000}, "bid": {"currencyCode": "JPY", "units": "80", "nanos": 970000000}, "mid": {"currencyCode": "JPY", "units": "82", "nanos": 970000000}}, {"providerCode": "MUFG", "date": {"year": 2018, "month": 7, "day": 23}, "baseCurrencyCode": "AUD", "quoteCurrencyCode": "JPY", "ask": {"currencyCode": "JPY", "units": "84", "nanos": 400000000}, "bid": {"currencyCode": "JPY", "units": "80", "nanos": 400000000}, "mid": {"currencyCode": "JPY", "units": "82", "nanos": 400000000}}, {"providerCode": "MUFG", "date": {"year": 2018, "month": 7, "day": 24}, "baseCurrencyCode": "AUD", "quoteCurrencyCode": "JPY", "ask": {"currencyCode": "JPY", "units": "84", "nanos": 40000000}, "bid": {"currencyCode": "JPY", "units": "80", "nanos": 40000000}, "mid": {"currencyCode": "JPY", "units": "82", "nanos": 40000000}}, {"providerCode": "MUFG", "date": {"year": 2018, "month": 7, "day": 25}, "baseCurrencyCode": "AUD", "quoteCurrencyCode": "JPY", "ask": {"currencyCode": "JPY", "units": "84", "nanos": 730000000}, "bid": {"currencyCode": "JPY", "units": "80", "nanos": 730000000}, "mid": {"currencyCode": "JPY", "units": "82", "nanos": 730000000}}, {"providerCode": "MUFG", "date": {"year": 2018, "month": 7, "day": 26}, "baseCurrencyCode": "AUD", "quoteCurrencyCode": "JPY", "ask": {"currencyCode": "JPY", "units": "84", "nanos": 600000000}, "bid": {"currencyCode": "JPY", "units": "80", "nanos": 600000000}, "mid": {"currencyCode": "JPY", "units": "82", "nanos": 600000000}}, {"providerCode": "MUFG", "date": {"year": 2018, "month": 7, "day": 27}, "baseCurrencyCode": "AUD", "quoteCurrencyCode": "JPY", "ask": {"currencyCode": "JPY", "units": "83", "nanos": 920000000}, "bid": {"currencyCode": "JPY", "units": "79", "nanos": 920000000}, "mid": {"currencyCode": "JPY", "units": "81", "nanos": 920000000}}, {"providerCode": "MUFG", "date": {"year": 2018, "month": 7, "day": 30}, "baseCurrencyCode": "AUD", "quoteCurrencyCode": "JPY", "ask": {"currencyCode": "JPY", "units": "84", "nanos": 210000000}, "bid": {"currencyCode": "JPY", "units": "80", "nanos": 210000000}, "mid": {"currencyCode": "JPY", "units": "82", "nanos": 210000000}}, {"providerCode": "MUFG", "date": {"year": 2018, "month": 7, "day": 31}, "baseCurrencyCode": "AUD", "quoteCurrencyCode": "JPY", "ask": {"currencyCode": "JPY", "units": "84", "nanos": 210000000}, "bid": {"currencyCode": "JPY", "units": "80", "nanos": 210000000}, "mid": {"currencyCode": "JPY", "units": "82", "nanos": 210000000}}]