[{"providerCode": "MUFG", "date": {"year": 2020, "month": 11, "day": 2}, "baseCurrencyCode": "TRY", "quoteCurrencyCode": "JPY", "ask": {"currencyCode": "JPY", "units": "15", "nanos": 10000000}, "bid": {"currencyCode": "JPY", "units": "10", "nanos": 10000000}, "mid": {"currencyCode": "JPY", "units": "12", "nanos": 510000000}}, {"providerCode": "MUFG", "date": {"year": 2020, "month": 11, "day": 4}, "baseCurrencyCode": "TRY", "quoteCurrencyCode": "JPY", "ask": {"currencyCode": "JPY", "units": "14", "nanos": 830000000}, "bid": {"currencyCode": "JPY", "units": "9", "nanos": 830000000}, "mid": {"currencyCode": "JPY", "units": "12", "nanos": 330000000}}, {"providerCode": "MUFG", "date": {"year": 2020, "month": 11, "day": 5}, "baseCurrencyCode": "TRY", "quoteCurrencyCode": "JPY", "ask": {"currencyCode": "JPY", "units": "14", "nanos": 920000000}, "bid": {"currencyCode": "JPY", "units": "9", "nanos": 920000000}, "mid": {"currencyCode": "JPY", "units": "12", "nanos": 420000000}}, {"providerCode": "MUFG", "date": {"year": 2020, "month": 11, "day": 6}, "baseCurrencyCode": "TRY", "quoteCurrencyCode": "JPY", "ask": {"currencyCode": "JPY", "units": "14", "nanos": 800000000}, "bid": {"currencyCode": "JPY", "units": "9", "nanos": 800000000}, "mid": {"currencyCode": "JPY", "units": "12", "nanos": 300000000}}, {"providerCode": "MUFG", "date": {"year": 2020, "month": 11, "day": 9}, "baseCurrencyCode": "TRY", "quoteCurrencyCode": "JPY", "ask": {"currencyCode": "JPY", "units": "14", "nanos": 780000000}, "bid": {"currencyCode": "JPY", "units": "9", "nanos": 780000000}, "mid": {"currencyCode": "JPY", "units": "12", "nanos": 280000000}}, {"providerCode": "MUFG", "date": {"year": 2020, "month": 11, "day": 10}, "baseCurrencyCode": "TRY", "quoteCurrencyCode": "JPY", "ask": {"currencyCode": "JPY", "units": "15", "nanos": 520000000}, "bid": {"currencyCode": "JPY", "units": "10", "nanos": 520000000}, "mid": {"currencyCode": "JPY", "units": "13", "nanos": 20000000}}, {"providerCode": "MUFG", "date": {"year": 2020, "month": 11, "day": 11}, "baseCurrencyCode": "TRY", "quoteCurrencyCode": "JPY", "ask": {"currencyCode": "JPY", "units": "15", "nanos": 310000000}, "bid": {"currencyCode": "JPY", "units": "10", "nanos": 310000000}, "mid": {"currencyCode": "JPY", "units": "12", "nanos": 810000000}}, {"providerCode": "MUFG", "date": {"year": 2020, "month": 11, "day": 12}, "baseCurrencyCode": "TRY", "quoteCurrencyCode": "JPY", "ask": {"currencyCode": "JPY", "units": "16", "nanos": 30000000}, "bid": {"currencyCode": "JPY", "units": "11", "nanos": 30000000}, "mid": {"currencyCode": "JPY", "units": "13", "nanos": 530000000}}, {"providerCode": "MUFG", "date": {"year": 2020, "month": 11, "day": 13}, "baseCurrencyCode": "TRY", "quoteCurrencyCode": "JPY", "ask": {"currencyCode": "JPY", "units": "16", "nanos": 120000000}, "bid": {"currencyCode": "JPY", "units": "11", "nanos": 120000000}, "mid": {"currencyCode": "JPY", "units": "13", "nanos": 620000000}}, {"providerCode": "MUFG", "date": {"year": 2020, "month": 11, "day": 16}, "baseCurrencyCode": "TRY", "quoteCurrencyCode": "JPY", "ask": {"currencyCode": "JPY", "units": "16", "nanos": 140000000}, "bid": {"currencyCode": "JPY", "units": "11", "nanos": 140000000}, "mid": {"currencyCode": "JPY", "units": "13", "nanos": 640000000}}, {"providerCode": "MUFG", "date": {"year": 2020, "month": 11, "day": 17}, "baseCurrencyCode": "TRY", "quoteCurrencyCode": "JPY", "ask": {"currencyCode": "JPY", "units": "16", "nanos": 50000000}, "bid": {"currencyCode": "JPY", "units": "11", "nanos": 50000000}, "mid": {"currencyCode": "JPY", "units": "13", "nanos": 550000000}}, {"providerCode": "MUFG", "date": {"year": 2020, "month": 11, "day": 18}, "baseCurrencyCode": "TRY", "quoteCurrencyCode": "JPY", "ask": {"currencyCode": "JPY", "units": "16", "nanos": 60000000}, "bid": {"currencyCode": "JPY", "units": "11", "nanos": 60000000}, "mid": {"currencyCode": "JPY", "units": "13", "nanos": 560000000}}, {"providerCode": "MUFG", "date": {"year": 2020, "month": 11, "day": 19}, "baseCurrencyCode": "TRY", "quoteCurrencyCode": "JPY", "ask": {"currencyCode": "JPY", "units": "15", "nanos": 940000000}, "bid": {"currencyCode": "JPY", "units": "10", "nanos": 940000000}, "mid": {"currencyCode": "JPY", "units": "13", "nanos": 440000000}}, {"providerCode": "MUFG", "date": {"year": 2020, "month": 11, "day": 20}, "baseCurrencyCode": "TRY", "quoteCurrencyCode": "JPY", "ask": {"currencyCode": "JPY", "units": "16", "nanos": 320000000}, "bid": {"currencyCode": "JPY", "units": "11", "nanos": 320000000}, "mid": {"currencyCode": "JPY", "units": "13", "nanos": 820000000}}, {"providerCode": "MUFG", "date": {"year": 2020, "month": 11, "day": 24}, "baseCurrencyCode": "TRY", "quoteCurrencyCode": "JPY", "ask": {"currencyCode": "JPY", "units": "15", "nanos": 780000000}, "bid": {"currencyCode": "JPY", "units": "10", "nanos": 780000000}, "mid": {"currencyCode": "JPY", "units": "13", "nanos": 280000000}}, {"providerCode": "MUFG", "date": {"year": 2020, "month": 11, "day": 25}, "baseCurrencyCode": "TRY", "quoteCurrencyCode": "JPY", "ask": {"currencyCode": "JPY", "units": "15", "nanos": 550000000}, "bid": {"currencyCode": "JPY", "units": "10", "nanos": 550000000}, "mid": {"currencyCode": "JPY", "units": "13", "nanos": 50000000}}, {"providerCode": "MUFG", "date": {"year": 2020, "month": 11, "day": 26}, "baseCurrencyCode": "TRY", "quoteCurrencyCode": "JPY", "ask": {"currencyCode": "JPY", "units": "15", "nanos": 610000000}, "bid": {"currencyCode": "JPY", "units": "10", "nanos": 610000000}, "mid": {"currencyCode": "JPY", "units": "13", "nanos": 110000000}}, {"providerCode": "MUFG", "date": {"year": 2020, "month": 11, "day": 27}, "baseCurrencyCode": "TRY", "quoteCurrencyCode": "JPY", "ask": {"currencyCode": "JPY", "units": "15", "nanos": 750000000}, "bid": {"currencyCode": "JPY", "units": "10", "nanos": 750000000}, "mid": {"currencyCode": "JPY", "units": "13", "nanos": 250000000}}, {"providerCode": "MUFG", "date": {"year": 2020, "month": 11, "day": 30}, "baseCurrencyCode": "TRY", "quoteCurrencyCode": "JPY", "ask": {"currencyCode": "JPY", "units": "15", "nanos": 690000000}, "bid": {"currencyCode": "JPY", "units": "10", "nanos": 690000000}, "mid": {"currencyCode": "JPY", "units": "13", "nanos": 190000000}}]