[{"providerCode": "MUFG", "date": {"year": 2020, "month": 9, "day": 1}, "baseCurrencyCode": "CAD", "quoteCurrencyCode": "JPY", "ask": {"currencyCode": "JPY", "units": "82", "nanos": 820000000}, "bid": {"currencyCode": "JPY", "units": "79", "nanos": 620000000}, "mid": {"currencyCode": "JPY", "units": "81", "nanos": 220000000}}, {"providerCode": "MUFG", "date": {"year": 2020, "month": 9, "day": 2}, "baseCurrencyCode": "CAD", "quoteCurrencyCode": "JPY", "ask": {"currencyCode": "JPY", "units": "82", "nanos": 740000000}, "bid": {"currencyCode": "JPY", "units": "79", "nanos": 540000000}, "mid": {"currencyCode": "JPY", "units": "81", "nanos": 140000000}}, {"providerCode": "MUFG", "date": {"year": 2020, "month": 9, "day": 3}, "baseCurrencyCode": "CAD", "quoteCurrencyCode": "JPY", "ask": {"currencyCode": "JPY", "units": "82", "nanos": 970000000}, "bid": {"currencyCode": "JPY", "units": "79", "nanos": 770000000}, "mid": {"currencyCode": "JPY", "units": "81", "nanos": 370000000}}, {"providerCode": "MUFG", "date": {"year": 2020, "month": 9, "day": 4}, "baseCurrencyCode": "CAD", "quoteCurrencyCode": "JPY", "ask": {"currencyCode": "JPY", "units": "82", "nanos": 500000000}, "bid": {"currencyCode": "JPY", "units": "79", "nanos": 300000000}, "mid": {"currencyCode": "JPY", "units": "80", "nanos": 900000000}}, {"providerCode": "MUFG", "date": {"year": 2020, "month": 9, "day": 7}, "baseCurrencyCode": "CAD", "quoteCurrencyCode": "JPY", "ask": {"currencyCode": "JPY", "units": "82", "nanos": 930000000}, "bid": {"currencyCode": "JPY", "units": "79", "nanos": 730000000}, "mid": {"currencyCode": "JPY", "units": "81", "nanos": 330000000}}, {"providerCode": "MUFG", "date": {"year": 2020, "month": 9, "day": 8}, "baseCurrencyCode": "CAD", "quoteCurrencyCode": "JPY", "ask": {"currencyCode": "JPY", "units": "82", "nanos": 720000000}, "bid": {"currencyCode": "JPY", "units": "79", "nanos": 520000000}, "mid": {"currencyCode": "JPY", "units": "81", "nanos": 120000000}}, {"providerCode": "MUFG", "date": {"year": 2020, "month": 9, "day": 9}, "baseCurrencyCode": "CAD", "quoteCurrencyCode": "JPY", "ask": {"currencyCode": "JPY", "units": "81", "nanos": 710000000}, "bid": {"currencyCode": "JPY", "units": "78", "nanos": 510000000}, "mid": {"currencyCode": "JPY", "units": "80", "nanos": 110000000}}, {"providerCode": "MUFG", "date": {"year": 2020, "month": 9, "day": 10}, "baseCurrencyCode": "CAD", "quoteCurrencyCode": "JPY", "ask": {"currencyCode": "JPY", "units": "82", "nanos": 300000000}, "bid": {"currencyCode": "JPY", "units": "79", "nanos": 100000000}, "mid": {"currencyCode": "JPY", "units": "80", "nanos": 700000000}}, {"providerCode": "MUFG", "date": {"year": 2020, "month": 9, "day": 11}, "baseCurrencyCode": "CAD", "quoteCurrencyCode": "JPY", "ask": {"currencyCode": "JPY", "units": "82", "nanos": 110000000}, "bid": {"currencyCode": "JPY", "units": "78", "nanos": 910000000}, "mid": {"currencyCode": "JPY", "units": "80", "nanos": 510000000}}, {"providerCode": "MUFG", "date": {"year": 2020, "month": 9, "day": 14}, "baseCurrencyCode": "CAD", "quoteCurrencyCode": "JPY", "ask": {"currencyCode": "JPY", "units": "82", "nanos": 120000000}, "bid": {"currencyCode": "JPY", "units": "78", "nanos": 920000000}, "mid": {"currencyCode": "JPY", "units": "80", "nanos": 520000000}}, {"providerCode": "MUFG", "date": {"year": 2020, "month": 9, "day": 15}, "baseCurrencyCode": "CAD", "quoteCurrencyCode": "JPY", "ask": {"currencyCode": "JPY", "units": "81", "nanos": 800000000}, "bid": {"currencyCode": "JPY", "units": "78", "nanos": 600000000}, "mid": {"currencyCode": "JPY", "units": "80", "nanos": 200000000}}, {"providerCode": "MUFG", "date": {"year": 2020, "month": 9, "day": 16}, "baseCurrencyCode": "CAD", "quoteCurrencyCode": "JPY", "ask": {"currencyCode": "JPY", "units": "81", "nanos": 450000000}, "bid": {"currencyCode": "JPY", "units": "78", "nanos": 250000000}, "mid": {"currencyCode": "JPY", "units": "79", "nanos": 850000000}}, {"providerCode": "MUFG", "date": {"year": 2020, "month": 9, "day": 17}, "baseCurrencyCode": "CAD", "quoteCurrencyCode": "JPY", "ask": {"currencyCode": "JPY", "units": "81", "nanos": 160000000}, "bid": {"currencyCode": "JPY", "units": "77", "nanos": 960000000}, "mid": {"currencyCode": "JPY", "units": "79", "nanos": 560000000}}, {"providerCode": "MUFG", "date": {"year": 2020, "month": 9, "day": 18}, "baseCurrencyCode": "CAD", "quoteCurrencyCode": "JPY", "ask": {"currencyCode": "JPY", "units": "81", "nanos": 270000000}, "bid": {"currencyCode": "JPY", "units": "78", "nanos": 70000000}, "mid": {"currencyCode": "JPY", "units": "79", "nanos": 670000000}}, {"providerCode": "MUFG", "date": {"year": 2020, "month": 9, "day": 23}, "baseCurrencyCode": "CAD", "quoteCurrencyCode": "JPY", "ask": {"currencyCode": "JPY", "units": "80", "nanos": 590000000}, "bid": {"currencyCode": "JPY", "units": "77", "nanos": 390000000}, "mid": {"currencyCode": "JPY", "units": "78", "nanos": 990000000}}, {"providerCode": "MUFG", "date": {"year": 2020, "month": 9, "day": 24}, "baseCurrencyCode": "CAD", "quoteCurrencyCode": "JPY", "ask": {"currencyCode": "JPY", "units": "80", "nanos": 390000000}, "bid": {"currencyCode": "JPY", "units": "77", "nanos": 190000000}, "mid": {"currencyCode": "JPY", "units": "78", "nanos": 790000000}}, {"providerCode": "MUFG", "date": {"year": 2020, "month": 9, "day": 25}, "baseCurrencyCode": "CAD", "quoteCurrencyCode": "JPY", "ask": {"currencyCode": "JPY", "units": "80", "nanos": 670000000}, "bid": {"currencyCode": "JPY", "units": "77", "nanos": 470000000}, "mid": {"currencyCode": "JPY", "units": "79", "nanos": 70000000}}, {"providerCode": "MUFG", "date": {"year": 2020, "month": 9, "day": 28}, "baseCurrencyCode": "CAD", "quoteCurrencyCode": "JPY", "ask": {"currencyCode": "JPY", "units": "80", "nanos": 280000000}, "bid": {"currencyCode": "JPY", "units": "77", "nanos": 80000000}, "mid": {"currencyCode": "JPY", "units": "78", "nanos": 680000000}}, {"providerCode": "MUFG", "date": {"year": 2020, "month": 9, "day": 29}, "baseCurrencyCode": "CAD", "quoteCurrencyCode": "JPY", "ask": {"currencyCode": "JPY", "units": "80", "nanos": 420000000}, "bid": {"currencyCode": "JPY", "units": "77", "nanos": 220000000}, "mid": {"currencyCode": "JPY", "units": "78", "nanos": 820000000}}, {"providerCode": "MUFG", "date": {"year": 2020, "month": 9, "day": 30}, "baseCurrencyCode": "CAD", "quoteCurrencyCode": "JPY", "ask": {"currencyCode": "JPY", "units": "80", "nanos": 630000000}, "bid": {"currencyCode": "JPY", "units": "77", "nanos": 430000000}, "mid": {"currencyCode": "JPY", "units": "79", "nanos": 30000000}}]