[{"providerCode": "MUFG", "date": {"year": 2018, "month": 3, "day": 1}, "baseCurrencyCode": "CAD", "quoteCurrencyCode": "JPY", "ask": {"currencyCode": "JPY", "units": "84", "nanos": 710000000}, "bid": {"currencyCode": "JPY", "units": "81", "nanos": 510000000}, "mid": {"currencyCode": "JPY", "units": "83", "nanos": 110000000}}, {"providerCode": "MUFG", "date": {"year": 2018, "month": 3, "day": 2}, "baseCurrencyCode": "CAD", "quoteCurrencyCode": "JPY", "ask": {"currencyCode": "JPY", "units": "84", "nanos": 490000000}, "bid": {"currencyCode": "JPY", "units": "81", "nanos": 290000000}, "mid": {"currencyCode": "JPY", "units": "82", "nanos": 890000000}}, {"providerCode": "MUFG", "date": {"year": 2018, "month": 3, "day": 5}, "baseCurrencyCode": "CAD", "quoteCurrencyCode": "JPY", "ask": {"currencyCode": "JPY", "units": "83", "nanos": 520000000}, "bid": {"currencyCode": "JPY", "units": "80", "nanos": 320000000}, "mid": {"currencyCode": "JPY", "units": "81", "nanos": 920000000}}, {"providerCode": "MUFG", "date": {"year": 2018, "month": 3, "day": 6}, "baseCurrencyCode": "CAD", "quoteCurrencyCode": "JPY", "ask": {"currencyCode": "JPY", "units": "83", "nanos": 470000000}, "bid": {"currencyCode": "JPY", "units": "80", "nanos": 270000000}, "mid": {"currencyCode": "JPY", "units": "81", "nanos": 870000000}}, {"providerCode": "MUFG", "date": {"year": 2018, "month": 3, "day": 7}, "baseCurrencyCode": "CAD", "quoteCurrencyCode": "JPY", "ask": {"currencyCode": "JPY", "units": "83", "nanos": 160000000}, "bid": {"currencyCode": "JPY", "units": "79", "nanos": 960000000}, "mid": {"currencyCode": "JPY", "units": "81", "nanos": 560000000}}, {"providerCode": "MUFG", "date": {"year": 2018, "month": 3, "day": 8}, "baseCurrencyCode": "CAD", "quoteCurrencyCode": "JPY", "ask": {"currencyCode": "JPY", "units": "83", "nanos": 760000000}, "bid": {"currencyCode": "JPY", "units": "80", "nanos": 560000000}, "mid": {"currencyCode": "JPY", "units": "82", "nanos": 160000000}}, {"providerCode": "MUFG", "date": {"year": 2018, "month": 3, "day": 9}, "baseCurrencyCode": "CAD", "quoteCurrencyCode": "JPY", "ask": {"currencyCode": "JPY", "units": "84", "nanos": 340000000}, "bid": {"currencyCode": "JPY", "units": "81", "nanos": 140000000}, "mid": {"currencyCode": "JPY", "units": "82", "nanos": 740000000}}, {"providerCode": "MUFG", "date": {"year": 2018, "month": 3, "day": 12}, "baseCurrencyCode": "CAD", "quoteCurrencyCode": "JPY", "ask": {"currencyCode": "JPY", "units": "85", "nanos": 90000000}, "bid": {"currencyCode": "JPY", "units": "81", "nanos": 890000000}, "mid": {"currencyCode": "JPY", "units": "83", "nanos": 490000000}}, {"providerCode": "MUFG", "date": {"year": 2018, "month": 3, "day": 13}, "baseCurrencyCode": "CAD", "quoteCurrencyCode": "JPY", "ask": {"currencyCode": "JPY", "units": "84", "nanos": 430000000}, "bid": {"currencyCode": "JPY", "units": "81", "nanos": 230000000}, "mid": {"currencyCode": "JPY", "units": "82", "nanos": 830000000}}, {"providerCode": "MUFG", "date": {"year": 2018, "month": 3, "day": 14}, "baseCurrencyCode": "CAD", "quoteCurrencyCode": "JPY", "ask": {"currencyCode": "JPY", "units": "83", "nanos": 960000000}, "bid": {"currencyCode": "JPY", "units": "80", "nanos": 760000000}, "mid": {"currencyCode": "JPY", "units": "82", "nanos": 360000000}}, {"providerCode": "MUFG", "date": {"year": 2018, "month": 3, "day": 15}, "baseCurrencyCode": "CAD", "quoteCurrencyCode": "JPY", "ask": {"currencyCode": "JPY", "units": "83", "nanos": 440000000}, "bid": {"currencyCode": "JPY", "units": "80", "nanos": 240000000}, "mid": {"currencyCode": "JPY", "units": "81", "nanos": 840000000}}, {"providerCode": "MUFG", "date": {"year": 2018, "month": 3, "day": 16}, "baseCurrencyCode": "CAD", "quoteCurrencyCode": "JPY", "ask": {"currencyCode": "JPY", "units": "82", "nanos": 970000000}, "bid": {"currencyCode": "JPY", "units": "79", "nanos": 770000000}, "mid": {"currencyCode": "JPY", "units": "81", "nanos": 370000000}}, {"providerCode": "MUFG", "date": {"year": 2018, "month": 3, "day": 19}, "baseCurrencyCode": "CAD", "quoteCurrencyCode": "JPY", "ask": {"currencyCode": "JPY", "units": "82", "nanos": 440000000}, "bid": {"currencyCode": "JPY", "units": "79", "nanos": 240000000}, "mid": {"currencyCode": "JPY", "units": "80", "nanos": 840000000}}, {"providerCode": "MUFG", "date": {"year": 2018, "month": 3, "day": 20}, "baseCurrencyCode": "CAD", "quoteCurrencyCode": "JPY", "ask": {"currencyCode": "JPY", "units": "82", "nanos": 770000000}, "bid": {"currencyCode": "JPY", "units": "79", "nanos": 570000000}, "mid": {"currencyCode": "JPY", "units": "81", "nanos": 170000000}}, {"providerCode": "MUFG", "date": {"year": 2018, "month": 3, "day": 22}, "baseCurrencyCode": "CAD", "quoteCurrencyCode": "JPY", "ask": {"currencyCode": "JPY", "units": "83", "nanos": 550000000}, "bid": {"currencyCode": "JPY", "units": "80", "nanos": 350000000}, "mid": {"currencyCode": "JPY", "units": "81", "nanos": 950000000}}, {"providerCode": "MUFG", "date": {"year": 2018, "month": 3, "day": 23}, "baseCurrencyCode": "CAD", "quoteCurrencyCode": "JPY", "ask": {"currencyCode": "JPY", "units": "82", "nanos": 860000000}, "bid": {"currencyCode": "JPY", "units": "79", "nanos": 660000000}, "mid": {"currencyCode": "JPY", "units": "81", "nanos": 260000000}}, {"providerCode": "MUFG", "date": {"year": 2018, "month": 3, "day": 26}, "baseCurrencyCode": "CAD", "quoteCurrencyCode": "JPY", "ask": {"currencyCode": "JPY", "units": "83", "nanos": 220000000}, "bid": {"currencyCode": "JPY", "units": "80", "nanos": 20000000}, "mid": {"currencyCode": "JPY", "units": "81", "nanos": 620000000}}, {"providerCode": "MUFG", "date": {"year": 2018, "month": 3, "day": 27}, "baseCurrencyCode": "CAD", "quoteCurrencyCode": "JPY", "ask": {"currencyCode": "JPY", "units": "83", "nanos": 770000000}, "bid": {"currencyCode": "JPY", "units": "80", "nanos": 570000000}, "mid": {"currencyCode": "JPY", "units": "82", "nanos": 170000000}}, {"providerCode": "MUFG", "date": {"year": 2018, "month": 3, "day": 28}, "baseCurrencyCode": "CAD", "quoteCurrencyCode": "JPY", "ask": {"currencyCode": "JPY", "units": "83", "nanos": 530000000}, "bid": {"currencyCode": "JPY", "units": "80", "nanos": 330000000}, "mid": {"currencyCode": "JPY", "units": "81", "nanos": 930000000}}, {"providerCode": "MUFG", "date": {"year": 2018, "month": 3, "day": 29}, "baseCurrencyCode": "CAD", "quoteCurrencyCode": "JPY", "ask": {"currencyCode": "JPY", "units": "84", "nanos": 310000000}, "bid": {"currencyCode": "JPY", "units": "81", "nanos": 110000000}, "mid": {"currencyCode": "JPY", "units": "82", "nanos": 710000000}}, {"providerCode": "MUFG", "date": {"year": 2018, "month": 3, "day": 30}, "baseCurrencyCode": "CAD", "quoteCurrencyCode": "JPY", "ask": {"currencyCode": "JPY", "units": "83", "nanos": 980000000}, "bid": {"currencyCode": "JPY", "units": "80", "nanos": 780000000}, "mid": {"currencyCode": "JPY", "units": "82", "nanos": 380000000}}]