[{"providerCode": "MUFG", "date": {"year": 2016, "month": 10, "day": 3}, "baseCurrencyCode": "AED", "quoteCurrencyCode": "JPY", "ask": {"currencyCode": "JPY", "units": "28", "nanos": 340000000}, "bid": {"currencyCode": "JPY", "units": "26", "nanos": 980000000}, "mid": {"currencyCode": "JPY", "units": "27", "nanos": 660000000}}, {"providerCode": "MUFG", "date": {"year": 2016, "month": 10, "day": 4}, "baseCurrencyCode": "AED", "quoteCurrencyCode": "JPY", "ask": {"currencyCode": "JPY", "units": "28", "nanos": 520000000}, "bid": {"currencyCode": "JPY", "units": "27", "nanos": 160000000}, "mid": {"currencyCode": "JPY", "units": "27", "nanos": 840000000}}, {"providerCode": "MUFG", "date": {"year": 2016, "month": 10, "day": 5}, "baseCurrencyCode": "AED", "quoteCurrencyCode": "JPY", "ask": {"currencyCode": "JPY", "units": "28", "nanos": 710000000}, "bid": {"currencyCode": "JPY", "units": "27", "nanos": 350000000}, "mid": {"currencyCode": "JPY", "units": "28", "nanos": 30000000}}, {"providerCode": "MUFG", "date": {"year": 2016, "month": 10, "day": 6}, "baseCurrencyCode": "AED", "quoteCurrencyCode": "JPY", "ask": {"currencyCode": "JPY", "units": "28", "nanos": 890000000}, "bid": {"currencyCode": "JPY", "units": "27", "nanos": 530000000}, "mid": {"currencyCode": "JPY", "units": "28", "nanos": 210000000}}, {"providerCode": "MUFG", "date": {"year": 2016, "month": 10, "day": 7}, "baseCurrencyCode": "AED", "quoteCurrencyCode": "JPY", "ask": {"currencyCode": "JPY", "units": "28", "nanos": 970000000}, "bid": {"currencyCode": "JPY", "units": "27", "nanos": 610000000}, "mid": {"currencyCode": "JPY", "units": "28", "nanos": 290000000}}, {"providerCode": "MUFG", "date": {"year": 2016, "month": 10, "day": 11}, "baseCurrencyCode": "AED", "quoteCurrencyCode": "JPY", "ask": {"currencyCode": "JPY", "units": "29", "nanos": 40000000}, "bid": {"currencyCode": "JPY", "units": "27", "nanos": 680000000}, "mid": {"currencyCode": "JPY", "units": "28", "nanos": 360000000}}, {"providerCode": "MUFG", "date": {"year": 2016, "month": 10, "day": 12}, "baseCurrencyCode": "AED", "quoteCurrencyCode": "JPY", "ask": {"currencyCode": "JPY", "units": "28", "nanos": 950000000}, "bid": {"currencyCode": "JPY", "units": "27", "nanos": 590000000}, "mid": {"currencyCode": "JPY", "units": "28", "nanos": 270000000}}, {"providerCode": "MUFG", "date": {"year": 2016, "month": 10, "day": 13}, "baseCurrencyCode": "AED", "quoteCurrencyCode": "JPY", "ask": {"currencyCode": "JPY", "units": "29", "nanos": 210000000}, "bid": {"currencyCode": "JPY", "units": "27", "nanos": 850000000}, "mid": {"currencyCode": "JPY", "units": "28", "nanos": 530000000}}, {"providerCode": "MUFG", "date": {"year": 2016, "month": 10, "day": 14}, "baseCurrencyCode": "AED", "quoteCurrencyCode": "JPY", "ask": {"currencyCode": "JPY", "units": "29", "nanos": 20000000}, "bid": {"currencyCode": "JPY", "units": "27", "nanos": 660000000}, "mid": {"currencyCode": "JPY", "units": "28", "nanos": 340000000}}, {"providerCode": "MUFG", "date": {"year": 2016, "month": 10, "day": 17}, "baseCurrencyCode": "AED", "quoteCurrencyCode": "JPY", "ask": {"currencyCode": "JPY", "units": "29", "nanos": 120000000}, "bid": {"currencyCode": "JPY", "units": "27", "nanos": 760000000}, "mid": {"currencyCode": "JPY", "units": "28", "nanos": 440000000}}, {"providerCode": "MUFG", "date": {"year": 2016, "month": 10, "day": 18}, "baseCurrencyCode": "AED", "quoteCurrencyCode": "JPY", "ask": {"currencyCode": "JPY", "units": "28", "nanos": 990000000}, "bid": {"currencyCode": "JPY", "units": "27", "nanos": 630000000}, "mid": {"currencyCode": "JPY", "units": "28", "nanos": 310000000}}, {"providerCode": "MUFG", "date": {"year": 2016, "month": 10, "day": 19}, "baseCurrencyCode": "AED", "quoteCurrencyCode": "JPY", "ask": {"currencyCode": "JPY", "units": "28", "nanos": 870000000}, "bid": {"currencyCode": "JPY", "units": "27", "nanos": 510000000}, "mid": {"currencyCode": "JPY", "units": "28", "nanos": 190000000}}, {"providerCode": "MUFG", "date": {"year": 2016, "month": 10, "day": 20}, "baseCurrencyCode": "AED", "quoteCurrencyCode": "JPY", "ask": {"currencyCode": "JPY", "units": "28", "nanos": 850000000}, "bid": {"currencyCode": "JPY", "units": "27", "nanos": 490000000}, "mid": {"currencyCode": "JPY", "units": "28", "nanos": 170000000}}, {"providerCode": "MUFG", "date": {"year": 2016, "month": 10, "day": 21}, "baseCurrencyCode": "AED", "quoteCurrencyCode": "JPY", "ask": {"currencyCode": "JPY", "units": "29", "nanos": 100000000}, "bid": {"currencyCode": "JPY", "units": "27", "nanos": 740000000}, "mid": {"currencyCode": "JPY", "units": "28", "nanos": 420000000}}, {"providerCode": "MUFG", "date": {"year": 2016, "month": 10, "day": 24}, "baseCurrencyCode": "AED", "quoteCurrencyCode": "JPY", "ask": {"currencyCode": "JPY", "units": "29"}, "bid": {"currencyCode": "JPY", "units": "27", "nanos": 640000000}, "mid": {"currencyCode": "JPY", "units": "28", "nanos": 320000000}}, {"providerCode": "MUFG", "date": {"year": 2016, "month": 10, "day": 25}, "baseCurrencyCode": "AED", "quoteCurrencyCode": "JPY", "ask": {"currencyCode": "JPY", "units": "29", "nanos": 170000000}, "bid": {"currencyCode": "JPY", "units": "27", "nanos": 810000000}, "mid": {"currencyCode": "JPY", "units": "28", "nanos": 490000000}}, {"providerCode": "MUFG", "date": {"year": 2016, "month": 10, "day": 26}, "baseCurrencyCode": "AED", "quoteCurrencyCode": "JPY", "ask": {"currencyCode": "JPY", "units": "29", "nanos": 90000000}, "bid": {"currencyCode": "JPY", "units": "27", "nanos": 730000000}, "mid": {"currencyCode": "JPY", "units": "28", "nanos": 410000000}}, {"providerCode": "MUFG", "date": {"year": 2016, "month": 10, "day": 27}, "baseCurrencyCode": "AED", "quoteCurrencyCode": "JPY", "ask": {"currencyCode": "JPY", "units": "29", "nanos": 190000000}, "bid": {"currencyCode": "JPY", "units": "27", "nanos": 830000000}, "mid": {"currencyCode": "JPY", "units": "28", "nanos": 510000000}}, {"providerCode": "MUFG", "date": {"year": 2016, "month": 10, "day": 28}, "baseCurrencyCode": "AED", "quoteCurrencyCode": "JPY", "ask": {"currencyCode": "JPY", "units": "29", "nanos": 380000000}, "bid": {"currencyCode": "JPY", "units": "28", "nanos": 20000000}, "mid": {"currencyCode": "JPY", "units": "28", "nanos": 700000000}}, {"providerCode": "MUFG", "date": {"year": 2016, "month": 10, "day": 31}, "baseCurrencyCode": "AED", "quoteCurrencyCode": "JPY", "ask": {"currencyCode": "JPY", "units": "29", "nanos": 280000000}, "bid": {"currencyCode": "JPY", "units": "27", "nanos": 920000000}, "mid": {"currencyCode": "JPY", "units": "28", "nanos": 600000000}}]